dronesploit/VERSION.txt
dronesploit/__conf__.py
dronesploit/__info__.py
dronesploit/__init__.py
dronesploit/__main__.py
dronesploit/_src/banners/banner1.asc
dronesploit/_src/banners/banner2.asc
dronesploit/_src/banners/banner3.asc
dronesploit/_src/banners/banner4.asc
dronesploit/_src/banners/banner5.asc
dronesploit/_src/banners/banner6.asc
dronesploit/_src/commands/generic.py
dronesploit/_src/commands/wifi.py
dronesploit/_src/modules/auxiliary/wifi/crack.py
dronesploit/_src/modules/auxiliary/wifi/deauth.py
dronesploit/_src/modules/auxiliary/wifi/sniff.py
dronesploit/_src/modules/auxiliary/wifi/wordlist.txt
dronesploit/_src/modules/command/dji/tello.py
dronesploit/_src/modules/command/hobicco/cme.py
dronesploit/_src/modules/command/hobicco/flitt.py
dronesploit/_src/modules/exploit/hobbico/cme.py
dronesploit/_src/modules/exploit/hobbico/flitt.py
dronesploit/drones/__init__.py
dronesploit/drones/dji.py
dronesploit/drones/hobbico.py
dronesploit/generic/__init__.py
dronesploit/generic/decorators.py
dronesploit/generic/mixins.py
dronesploit/wifi/__init__.py
dronesploit/wifi/drone.py
dronesploit/wifi/mixin.py
dronesploit-1.1.16.dist-info/LICENSE
dronesploit-1.1.16.dist-info/METADATA
dronesploit-1.1.16.dist-info/WHEEL
dronesploit-1.1.16.dist-info/entry_points.txt
dronesploit-1.1.16.dist-info/top_level.txt
dronesploit-1.1.16.dist-info/RECORD
