Metadata-Version: 2.1
Name: dronesploit
Version: 1.1.16
Summary: Drone pentesting framework console
Author-email: Alexandre D'Hondt <alexandre.dhondt@gmail.com>
License:                     GNU GENERAL PUBLIC LICENSE
Project-URL: documentation, https://dronesploit.readthedocs.io/en/latest/?badge=latest
Project-URL: homepage, https://github.com/dhondta/dronesploit
Project-URL: issues, https://github.com/dhondta/dronesploit/issues
Project-URL: repository, https://github.com/dhondta/dronesploit
Keywords: python,drone,pentesting,framework
Classifier: Development Status :: 4 - Beta
Classifier: Environment :: Console
Classifier: Intended Audience :: Developers
Classifier: Intended Audience :: Information Technology
Classifier: License :: OSI Approved :: GNU General Public License v3 or later (GPLv3+)
Classifier: Programming Language :: Python :: 3
Classifier: Programming Language :: Python :: 3.8
Classifier: Programming Language :: Python :: 3.9
Classifier: Programming Language :: Python :: 3.10
Classifier: Programming Language :: Python :: 3.11
Classifier: Topic :: Software Development :: Libraries :: Python Modules
Requires-Python: <4,>=3.8
License-File: LICENSE
Requires-Dist: sploitkit>=0.5.8
